[
    {
        "title": "الخوف | أبُكاليبـس - الحرب العالمية الأولى",
        "category": "history",
        "id": "huyXH0lxpVM",
        "lang": "ar",
        "embed": "https://www.youtube-nocookie.com/embed/huyXH0lxpVM?autoplay=1&mute=1",
        "duration": "44:10"
    },
    {
        "title": "المعركة النهائية لهتلر: الكتيبة المفقودة",
        "category": "history",
        "id": "lE2B6DdFZBI",
        "lang": "ar",
        "embed": "https://www.youtube-nocookie.com/embed/lE2B6DdFZBI?autoplay=1&mute=1",
        "duration": "42:24"
    },
    {
        "title": "مصر القديمة: توت عنخ آمون الجبار",
        "category": "history",
        "id": "udE4ehMwChc",
        "lang": "ar",
        "embed": "https://www.youtube-nocookie.com/embed/udE4ehMwChc?autoplay=1&mute=1",
        "duration": "44:10"
    },
    
    {
        "title": "وثائقي | قوة الأفكار - لغز كبير يواجه العلم",
        "category": "science",
        "id": "ON7V2XiQFrM",
        "lang": "ar",
        "embed": "https://www.youtube-nocookie.com/embed/ON7V2XiQFrM?autoplay=1&mute=1",
        "duration": "25:56"
    },
    
    
    
    {
        "title": "أرض الناجون | الأرجنتين البرية ",
        "category": "الطبيعة والحياة البرية",
        "id": "Ioe_dnns6r0",
        "lang": "ar",
        "embed": "https://www.youtube-nocookie.com/embed/Ioe_dnns6r0?si=dfwG6YpX5FIt4iSu&autoplay=1&mute=1",
        "duration": "41:54"
    },
    {
        "title": "اكتشاف عالم المحيطات: المدن الغارقة",
        "category": "history",
        "id": "8zdcwa28KSc",
        "lang": "ar",
        "embed": "https://www.youtube-nocookie.com/embed/8zdcwa28KSc?autoplay=1&mute=1",
        "duration": "43:18"
    },
    {
        "title": "السباق نحو الذكاء الاصطناعيّ",
        "category": "technology",
        "id": "EpW4j-3sPP4",
        "lang": "ar",
        "embed": "https://www.youtube-nocookie.com/embed/EpW4j-3sPP4?autoplay=1&mute=1",
        "duration": "51:42"
    },
    {
        "title": "عصر البيانات.. الاستخدامات الملموسة للذكاء الصناعي في حياة البشر",
        "category": "technology",
        "id": "5bEBTUTX20M",
        "lang": "ar",
        "embed": "https://www.youtube-nocookie.com/embed/5bEBTUTX20M?autoplay=1&mute=1",
        "duration": "24:02"

    },
    {
        "title": "المريخ - العيش على الكوكب الأحمر؟",
        "category": "science",
        "id": "rtteGD7vQ2o",
        "lang": "ar",
        "embed": "https://www.youtube-nocookie.com/embed/rtteGD7vQ2o?autoplay=1&mute=1",
        "duration": "42:26"
    },
    {
        "title": "هل سينقذنا الذكاء الاصطناعي أم سيهلكنا؟",
        "category": "technology",
        "id": "zLABTOk7Pb8",
        "lang": "ar",
        "embed": "https://www.youtube-nocookie.com/embed/zLABTOk7Pb8?autoplay=1&mute=1",
        "duration": "28:26"
    },
    {
        "title": " الذكاء الاصطناعي: سباق بين الصين والولايات المتحدة الأمريكية وأوروبا",
        "category": "technology",
        "id": "EUl-3wgfUuo",
        "lang": "ar",
        "embed": "https://www.youtube-nocookie.com/embed/EUl-3wgfUuo?autoplay=1&mute=1",
        "duration": "1:28:30"
    },
    {
        "title": "بين الإنسان والذكاء الاصطناعي: كيف تكتسب الروبوتات الوعي والسلوك البشري؟",
        "category": "technology",
        "id": "-5NTXo8fWfQ",
        "lang": "ar",
        "embed": "https://www.youtube-nocookie.com/embed/-5NTXo8fWfQ?autoplay=1&mute=1",
        "duration": "42:26"
    },
    {
        "title": "ذكاء الحشرات - كيف يطور النحل مهارات معقدة؟",
        "category": "الطبيعة والحياة البرية",
        "id": "46mIoIdGCDw",
        "lang": "ar",
        "embed": "https://www.youtube-nocookie.com/embed/46mIoIdGCDw?autoplay=1&mute=1",
        "duration": "42:25"
    },
    {
        "title": "هل يتحدث البشر والحيتان نفس اللغة ؟",
        "category": "الطبيعة والحياة البرية",
        "id": "cTNguGH4XdY",
        "lang": "ar",
        "embed": "https://www.youtube-nocookie.com/embed/cTNguGH4XdY?autoplay=1&mute=1",
        "duration": "42:26"
    },

    
    
    
    
    {
        "title": "قتلة البريّة | أشرس كائنات أفريقيا",
        "category": "الطبيعة والحياة البرية",
        "id": "aKbEjRP1rCs",
        "lang": "ar",
        "embed": "https://www.youtube-nocookie.com/embed/aKbEjRP1rCs?autoplay=1&mute=1",
        "duration": "44:00"
    },
    
    {
        "title": "كيف ستبدو مدن المستقبل؟ - آفاق جديدة للتخطيط الحضري وحماية مستدامة للمناخ",
        "category": "technology",
        "id": "FuQbR5WcU4Q",
        "lang": "ar",
        "embed": "https://www.youtube-nocookie.com/embed/FuQbR5WcU4Q?autoplay=1&mute=1",
        "duration": "25:55"
    },
    
    
    
    {
        "title": "معبد الإنكا المفقود",
        "category": "مجتمعات وثقافات",
        "id": "MdmD9X8FkUs",
        "lang": "ar",
        "embed": "https://www.youtube-nocookie.com/embed/MdmD9X8FkUs?si=lqQ7keunO3MyC17b&autoplay=1&mute=1",
        "duration": "42:08"
    },
    
    {
        "title": "اكتشافات مذهلة في عالم الفُطر: من تحليل البلاستيك إلى الطب",
        "category": "science",
        "id": "KoQNJNE8pAc",
        "lang": "ar",
        "embed": "https://www.youtube-nocookie.com/embed/KoQNJNE8pAc?si=FJWXZJBcLsi2ag0c&autoplay=1&mute=1",
        "duration": "40:35"
    },
    {
        "title": "| الصين ومدنها الكبرى العملاقة - صراع على السكن في الصين",
        "category": "مجتمعات وثقافات",
        "id": "cfirzn4il5A",
        "lang": "ar",
        "embed": "https://www.youtube-nocookie.com/embed/cfirzn4il5A?si=chOcQxmQmpKzSRW8&autoplay=1&mute=1",
        "duration": "42:27"
    },
    
    
    {
        "title": "الوجود الرقمي بعد الموت - \"خلود\" بفضل الذكاء الاصطناعي",
        "category": "technology",
        "id": "FMnm2cKfxb0",
        "lang": "ar",
        "embed": "https://www.youtube-nocookie.com/embed/FMnm2cKfxb0?autoplay=1&mute=1",
        "duration": "28:25"
    },
    {
        "title": "ما هو دور الأمعاء في جسد الإنسان؟ - تغذية ومناعة وصحة نفسية ",
        "category": "science",
        "id": "_98ItKGmIW8",
        "lang": "ar",
        "embed": "https://www.youtube-nocookie.com/embed/_98ItKGmIW8?autoplay=1&mute=1",
        "duration": "42:25"
    },
    {
        "title": "عودة بقّ الفراش إلى أوروبا: حرب الفنادق والمختصين ضد الحشرات الطفيلية",
        "category": "science",
        "id": "KfOSDkcM9zo",
        "lang": "ar",
        "embed": "https://www.youtube-nocookie.com/embed/KfOSDkcM9zo?autoplay=1&mute=1",
        "duration": "28:25"
    }
]
